precommit_diffcheck/__init__.py
precommit_diffcheck/py.typed
precommit_diffcheck-1.12.dist-info/LICENSE
precommit_diffcheck-1.12.dist-info/METADATA
precommit_diffcheck-1.12.dist-info/WHEEL
precommit_diffcheck-1.12.dist-info/top_level.txt
precommit_diffcheck-1.12.dist-info/RECORD
