Metadata-Version: 2.1
Name: precommit-diffcheck
Version: 1.12
Summary: A library for creating precommit hooks against file diffs
Home-page: https://github.com/EliRibble/precommit-diffcheck
Author: Eli Ribble
Author-email: eliribble@google.com
License: UNKNOWN
Platform: UNKNOWN
Classifier: Intended Audience :: Developers
Classifier: License :: OSI Approved :: MIT License
Classifier: Programming Language :: Python
Classifier: Programming Language :: Python :: 3.6
Requires-Python: >=3.6
License-File: LICENSE
Requires-Dist: unidiff (==0.5.5)
Provides-Extra: develop
Requires-Dist: mypy ; extra == 'develop'
Requires-Dist: nose2 ; extra == 'develop'
Requires-Dist: pylint ; extra == 'develop'
Requires-Dist: twine ; extra == 'develop'
Requires-Dist: wheel ; extra == 'develop'
